setuptools_gitver/__init__.py
setuptools_gitver-1.1.0.dist-info/DESCRIPTION.rst
setuptools_gitver-1.1.0.dist-info/LICENSE.txt
setuptools_gitver-1.1.0.dist-info/METADATA
setuptools_gitver-1.1.0.dist-info/RECORD
setuptools_gitver-1.1.0.dist-info/WHEEL
setuptools_gitver-1.1.0.dist-info/entry_points.txt
setuptools_gitver-1.1.0.dist-info/metadata.json
setuptools_gitver-1.1.0.dist-info/top_level.txt
setuptools_gitver-1.1.0.dist-info/zip-safe
