Metadata-Version: 2.0
Name: setuptools-gitver
Version: 1.1.0
Summary: Simple Git version plugin for setuptools
Home-page: https://github.com/suutari/setuptools-gitver
Author: Tuomas Suutari
Author-email: tuomas@nepnep.net
License: MIT
Keywords: git,version,describe,tag,setuptools
Platform: UNKNOWN
Classifier: Development Status :: 4 - Beta
Classifier: Intended Audience :: Developers
Classifier: Topic :: Software Development :: Libraries :: Python Modules
Classifier: Topic :: System :: Archiving :: Packaging
Classifier: License :: OSI Approved :: MIT License
Classifier: Programming Language :: Python :: 2
Classifier: Programming Language :: Python :: 2.7
Classifier: Programming Language :: Python :: 3
Classifier: Programming Language :: Python :: 3.4
Classifier: Programming Language :: Python :: 3.5
Classifier: Programming Language :: Python :: 3.6
